py_netgames_server/__init__.py
py_netgames_server/__main__.py
py_netgames_server/game_server.py
py_netgames_server/match.py
py_netgames_server/websocket_server_builder.py
py_netgames_server-0.0.4.dist-info/LICENSE.txt
py_netgames_server-0.0.4.dist-info/METADATA
py_netgames_server-0.0.4.dist-info/WHEEL
py_netgames_server-0.0.4.dist-info/top_level.txt
py_netgames_server-0.0.4.dist-info/RECORD
