Metadata-Version: 2.1
Name: py-netgames-server
Version: 0.0.4
Summary: Py-NetGames Server
Author-email: Gabriel Machado da Roza <gabrielmachadodaroza@outlook.com>
License: MIT License
License-File: LICENSE.txt
Requires-Dist: py-netgames-model
Requires-Dist: websockets
